pstash/__init__.py
pstash/options.py
pstash/stashb.py
pstash/stashd.py
pstash-0.1.4.dist-info/METADATA
pstash-0.1.4.dist-info/WHEEL
pstash-0.1.4.dist-info/top_level.txt
pstash-0.1.4.dist-info/RECORD
